brkraw_viewer/__init__.py
brkraw_viewer/cli_viewer.py
brkraw_viewer/cli_viewer_config.py
brkraw_viewer/app/__init__.py
brkraw_viewer/app/bootstrap.py
brkraw_viewer/app/protocols.py
brkraw_viewer/app/state.py
brkraw_viewer/app/controller/__init__.py
brkraw_viewer/app/controller/dataset.py
brkraw_viewer/app/controller/helper.py
brkraw_viewer/app/controller/viewer.py
brkraw_viewer/app/services/__init__.py
brkraw_viewer/app/services/hooks.py
brkraw_viewer/app/services/registry.py
brkraw_viewer/app/services/viewer_config.py
brkraw_viewer/app/services/worker_manager.py
brkraw_viewer/app/workers/__init__.py
brkraw_viewer/app/workers/convert_worker.py
brkraw_viewer/app/workers/protocol.py
brkraw_viewer/app/workers/shm.py
brkraw_viewer/assets/icon.ico
brkraw_viewer/assets/icon.png
brkraw_viewer/assets/registry.png
brkraw_viewer/assets/viewport-capture.png
brkraw_viewer/assets/worker-logs.png
brkraw_viewer/ui/__init__.py
brkraw_viewer/ui/assets.py
brkraw_viewer/ui/sharedtypes.py
brkraw_viewer/ui/components/icon_button.py
brkraw_viewer/ui/components/label_painter.py
brkraw_viewer/ui/components/plotter.py
brkraw_viewer/ui/components/viewport.py
brkraw_viewer/ui/main/__init__.py
brkraw_viewer/ui/main/sidebar.py
brkraw_viewer/ui/main/status.py
brkraw_viewer/ui/main/subject_bar.py
brkraw_viewer/ui/main/tabs.py
brkraw_viewer/ui/main/top.py
brkraw_viewer/ui/main/window.py
brkraw_viewer/ui/tabs/__init__.py
brkraw_viewer/ui/tabs/registry.py
brkraw_viewer/ui/tabs/addons/__init__.py
brkraw_viewer/ui/tabs/addons/window.py
brkraw_viewer/ui/tabs/config/__init__.py
brkraw_viewer/ui/tabs/config/window.py
brkraw_viewer/ui/tabs/convert/__init__.py
brkraw_viewer/ui/tabs/convert/window.py
brkraw_viewer/ui/tabs/extensions/__init__.py
brkraw_viewer/ui/tabs/extensions/window.py
brkraw_viewer/ui/tabs/params/__init__.py
brkraw_viewer/ui/tabs/params/window.py
brkraw_viewer/ui/tabs/viewer/__init__.py
brkraw_viewer/ui/tabs/viewer/left_panel.py
brkraw_viewer/ui/tabs/viewer/right_panel.py
brkraw_viewer-0.4.1.dist-info/METADATA
brkraw_viewer-0.4.1.dist-info/WHEEL
brkraw_viewer-0.4.1.dist-info/entry_points.txt
brkraw_viewer-0.4.1.dist-info/top_level.txt
brkraw_viewer-0.4.1.dist-info/RECORD
