Metadata-Version: 2.4
Name: brkraw-viewer
Version: 0.4.1
Summary: BrkRaw scan viewer plugin for brkraw CLI.
Author: BrkRaw
License: MIT
Classifier: Programming Language :: Python :: 3
Classifier: License :: OSI Approved :: MIT License
Classifier: Operating System :: OS Independent
Requires-Python: >=3.9
Requires-Dist: brkraw>=0.5.5
Requires-Dist: nibabel>=5.0
Requires-Dist: pillow>=10.0
Requires-Dist: ruamel.yaml>=0.17.0
Provides-Extra: docs
Requires-Dist: mkdocs-material>=9.5.0; extra == "docs"
Provides-Extra: test
Requires-Dist: pytest>=7.4; extra == "test"
